aksub/__init__.py
aksub/subscriber.py
aksub-0.1.1.dist-info/METADATA
aksub-0.1.1.dist-info/WHEEL
aksub-0.1.1.dist-info/top_level.txt
aksub-0.1.1.dist-info/RECORD
