Metadata-Version: 2.4
Name: aksub
Version: 0.1.1
Summary: A generic ROS2 subscriber for numbers, strings, images, and video.
Author: akshay
Author-email: akshayfusion1@gmail.com
Requires-Python: >=3.6
Requires-Dist: setuptools
Requires-Dist: cv_bridge
Dynamic: author
Dynamic: author-email
Dynamic: description
Dynamic: description-content-type
Dynamic: requires-dist
Dynamic: requires-python
Dynamic: summary
